wsgicas/__init__.py
wsgicas/middleware.py
wsgicas/tests/__init__.py
wsgicas/tests/test_middleware.py
wsgicas-0.2.dist-info/LICENSE
wsgicas-0.2.dist-info/METADATA
wsgicas-0.2.dist-info/WHEEL
wsgicas-0.2.dist-info/top_level.txt
wsgicas-0.2.dist-info/RECORD
